{
    "MapHeight" : 10,
    "MapWidth" : 15,
    "Cellsize" : 10,
    "Levels" : { 
        "BombermanSolo": [
            {
                "indexname": "BombermanSolo1",
                "index": 0,
                "tiles": [
                    "blocker|blocker|blocker|blocker|blocker|blocker|blocker|blocker|blocker|blocker|blocker|blocker|blocker|blocker|blocker|blocker",
                    "blocker|tile|breakable|breakable|tile|tile|tile|tile|tile|tile|tile|breakable|tile|tile|tile|blocker",
                    "blocker|tile|blocker|tile|blocker|tile|blocker|tile|blocker|tile|blocker|tile|blocker|breakable|tile|blocker",
                    "blocker|tile|tile|tile|breakable|breakable|tile|tile|tile|tile|tile|tile|tile|tile|tile|blocker",
                    "blocker|tile|blocker|tile|blocker|tile|blocker|tile|blocker|tile|blocker|tile|blocker|tile|tile|blocker",
                    "blocker|tile|tile|tile|tile|spawn|tile|tile|tile|tile|tile|extraBomb|tile|tile|tile|blocker",
                    "blocker|tile|blocker|tile|blocker|tile|blocker|tile|blocker|tile|blocker|tile|blocker|breakable|tile|blocker",
                    "blocker|tile|tile|tile|tile|tile|tile|breakable|tile|breakable|tile|tile|tile|tile|tile|blocker",
                    "blocker|tile|blocker|tile|blocker|tile|blocker|tile|blocker|tile|blocker|tile|blocker|tile|breakable|blocker",
                    "blocker|tile|tile|tile|tile|tile|breakable|tile|tile|tile|tile|tile|breakable|tile|tile|blocker",
                    "blocker|tile|blocker|breakable|blocker|tile|blocker|tile|blocker|tile|blocker|tile|blocker|tile|tile|blocker",
                    "blocker|tile|tile|breakable|tile|tile|tile|tile|tile|tile|breakable|tile|tile|tile|tile|blocker",
                    "blocker|blocker|blocker|blocker|blocker|blocker|blocker|blocker|blocker|blocker|blocker|blocker|blocker|blocker|blocker|blocker"
                ]
            },
            {
                "indexname": "BombermanSolo2",
                "index": 1,
                "tiles": [
                    "undug|undug|undug|undug|undug|undug|undug|undug|undug|undug|undug|undug|undug|undug",
                    "undug|enemySpawn|undug|undug|undug|undug|undug|rock|undug|undug|undug|undug|enemySpawn|undug",
                    "undug|dug|undug|undug|undug|undug|undug|undug|undug|undug|undug|undug|dug|undug",
                    "undug|dug|dug|dug|undug|undug|undug|undug|undug|undug|dug|dug|dug|undug",
                    "undug|undug|undug|undug|rock|undug|rock|undug|undug|undug|undug|undug|undug|undug",
                    "undug|undug|undug|undug|undug|undug|undug|undug|undug|undug|undug|undug|undug|undug",
                    "undug|undug|undug|undug|undug|undug|undug|undug|undug|undug|undug|undug|undug|undug",
                    "undug|dug|enemySpawn|dug|undug|undug|undug|undug|undug|undug|undug|undug|undug|undug",
                    "undug|undug|undug|undug|dug|dug|spawn|dug|dug|undug|undug|undug|undug|undug",
                    "undug|undug|undug|undug|undug|undug|undug|undug|undug|undug|undug|undug|undug|undug"
                ]
            },
            {
                "indexname": "BombermanSolo3",
                "index": 2,
                "tiles": [
                    "undug|undug|undug|undug|undug|undug|undug|undug|undug|undug|undug|undug|undug|undug",
                    "dug|enemySpawn|dug|undug|undug|undug|undug|undug|undug|undug|undug|undug|rock|undug",
                    "undug|undug|undug|undug|undug|undug|undug|undug|undug|undug|undug|undug|undug|undug",
                    "undug|undug|undug|undug|rock|undug|undug|undug|enemySpawn|dug|dug|undug|undug|undug",
                    "undug|undug|undug|undug|undug|undug|undug|undug|undug|undug|dug|undug|undug|undug",
                    "undug|undug|undug|undug|undug|rock|undug|undug|undug|undug|dug|undug|undug|undug",
                    "undug|undug|dug|dug|spawn|dug|undug|undug|undug|undug|dug|dug|enemySpawn|undug",
                    "undug|undug|enemySpawn|undug|undug|undug|undug|undug|undug|undug|undug|undug|undug|undug",
                    "undug|enemySpawn|dug|undug|undug|undug|undug|undug|undug|dug|enemySpawn|dug|undug|undug",
                    "undug|undug|undug|undug|undug|undug|undug|undug|undug|undug|undug|undug|undug|undug"
                ]
            }    
        ],
        "BombermanVersus":[
            {
                "indexname": "BombermanVersus",
                "index": 0,
                "tiles": [
                    "undug|undug|undug|undug|undug|undug|undug|undug|rock|undug|undug|undug|undug|undug",
                    "undug|undug|undug|undug|rock|undug|undug|undug|undug|undug|undug|undug|undug|undug",
                    "undug|undug|dug|dug|dug|dug|dug|dug|dug|dug|dug|dug|undug|undug",
                    "undug|undug|dug|dug|dug|dug|dug|dug|dug|dug|dug|dug|undug|undug",
                    "undug|undug|dug|undug|undug|undug|undug|rock|undug|undug|undug|dug|undug|undug",
                    "undug|undug|dug|dug|dug|dug|dug|dug|dug|dug|dug|dug|undug|undug",
                    "undug|undug|dug|dug|dug|dug|dug|dug|dug|dug|dug|dug|undug|undug",
                    "undug|undug|dug|undug|undug|undug|undug|undug|undug|undug|undug|dug|undug|undug",
                    "undug|dug|spawn|dug|dug|dug|dug|dug|dug|dug|dug|spawn|dug|undug",
                    "undug|undug|undug|undug|undug|undug|undug|undug|undug|undug|undug|undug|undug|undug"
                ]
            }
        ],
        "BombermanCoop":[
            {
                "indexname": "BombermanCoop",
                "index": 0,
                "tiles": [
                    "undug|undug|undug|undug|undug|undug|undug|undug|undug|undug|undug|undug|undug|undug",
                    "undug|dug|enemySpawn|dug|dug|undug|undug|undug|undug|dug|dug|enemySpawn|dug|undug",
                    "undug|undug|undug|undug|dug|undug|undug|undug|undug|dug|undug|undug|undug|undug",
                    "undug|undug|undug|undug|dug|undug|undug|undug|undug|dug|undug|undug|undug|undug",
                    "undug|undug|undug|undug|dug|enemySpawn|dug|enemySpawn|dug|dug|undug|undug|undug|undug",
                    "undug|undug|undug|undug|undug|undug|undug|undug|undug|undug|undug|undug|undug|undug",
                    "undug|undug|undug|undug|undug|undug|undug|undug|undug|undug|undug|undug|undug|undug",
                    "undug|undug|undug|undug|undug|undug|undug|undug|undug|undug|undug|undug|undug|undug",
                    "undug|dug|spawn|dug|undug|undug|undug|undug|undug|undug|dug|spawn|dug|undug",
                    "undug|undug|undug|undug|undug|undug|undug|undug|undug|undug|undug|undug|undug|undug"
                ]
            }
        ]
    }
}